ondewo/__init__.py
ondewo/nlu/__init__.py
ondewo/nlu/agent_pb2.py
ondewo/nlu/agent_pb2.pyi
ondewo/nlu/agent_pb2_grpc.py
ondewo/nlu/aiservices_pb2.py
ondewo/nlu/aiservices_pb2.pyi
ondewo/nlu/aiservices_pb2_grpc.py
ondewo/nlu/ccai_project_pb2.py
ondewo/nlu/ccai_project_pb2.pyi
ondewo/nlu/ccai_project_pb2_grpc.py
ondewo/nlu/common_pb2.py
ondewo/nlu/common_pb2.pyi
ondewo/nlu/common_pb2_grpc.py
ondewo/nlu/context_pb2.py
ondewo/nlu/context_pb2.pyi
ondewo/nlu/context_pb2_grpc.py
ondewo/nlu/entity_type_pb2.py
ondewo/nlu/entity_type_pb2.pyi
ondewo/nlu/entity_type_pb2_grpc.py
ondewo/nlu/intent_pb2.py
ondewo/nlu/intent_pb2.pyi
ondewo/nlu/intent_pb2_grpc.py
ondewo/nlu/operation_metadata_pb2.py
ondewo/nlu/operation_metadata_pb2.pyi
ondewo/nlu/operation_metadata_pb2_grpc.py
ondewo/nlu/operations_pb2.py
ondewo/nlu/operations_pb2.pyi
ondewo/nlu/operations_pb2_grpc.py
ondewo/nlu/project_role_pb2.py
ondewo/nlu/project_role_pb2.pyi
ondewo/nlu/project_role_pb2_grpc.py
ondewo/nlu/project_statistics_pb2.py
ondewo/nlu/project_statistics_pb2.pyi
ondewo/nlu/project_statistics_pb2_grpc.py
ondewo/nlu/server_statistics_pb2.py
ondewo/nlu/server_statistics_pb2.pyi
ondewo/nlu/server_statistics_pb2_grpc.py
ondewo/nlu/session_pb2.py
ondewo/nlu/session_pb2.pyi
ondewo/nlu/session_pb2_grpc.py
ondewo/nlu/user_pb2.py
ondewo/nlu/user_pb2.pyi
ondewo/nlu/user_pb2_grpc.py
ondewo/nlu/utility_pb2.py
ondewo/nlu/utility_pb2.pyi
ondewo/nlu/utility_pb2_grpc.py
ondewo/nlu/webhook_pb2.py
ondewo/nlu/webhook_pb2.pyi
ondewo/nlu/webhook_pb2_grpc.py
ondewo/qa/__init__.py
ondewo/qa/qa_pb2.py
ondewo/qa/qa_pb2.pyi
ondewo/qa/qa_pb2_grpc.py
ondewo/s2t/__init__.py
ondewo/s2t/speech_to_text_pb2.py
ondewo/s2t/speech_to_text_pb2.pyi
ondewo/s2t/speech_to_text_pb2_grpc.py
ondewo/sip/__init__.py
ondewo/sip/sip_pb2.py
ondewo/sip/sip_pb2.pyi
ondewo/sip/sip_pb2_grpc.py
ondewo/t2s/__init__.py
ondewo/t2s/text_to_speech_pb2.py
ondewo/t2s/text_to_speech_pb2.pyi
ondewo/t2s/text_to_speech_pb2_grpc.py
ondewo/vtsi/__init__.py
ondewo_vtsi_client-8.1.0.dist-info/LICENSE
ondewo_vtsi_client-8.1.0.dist-info/METADATA
ondewo_vtsi_client-8.1.0.dist-info/WHEEL
ondewo_vtsi_client-8.1.0.dist-info/top_level.txt
ondewo_vtsi_client-8.1.0.dist-info/RECORD
